[
  {
    "player": "Dan Quisenberry",
    "team1": "Kansas City Royals",
    "team2": "St. Louis Cardinals",
    "year": 1990
  },
  {
    "player": "Carney Lansford",
    "team1": "Anaheim Angels",
    "team2": "Oakland Athletics",
    "year": 1991
  },
  {
    "player": "Don Sutton",
    "team1": "Anaheim Angels",
    "team2": "Houston Astros",
    "year": 1986
  },
  {
    "player": "Brett Butler",
    "team1": "Atlanta Braves",
    "team2": "Cleveland Indians",
    "year": 1988
  },
  {
    "player": "Brett Butler",
    "team1": "Atlanta Braves",
    "team2": "Los Angeles Dodgers",
    "year": 1991
  },
  {
    "player": "Brett Butler",
    "team1": "Atlanta Braves",
    "team2": "San Francisco Giants",
    "year": 1989
  },
  {
    "player": "Brett Butler",
    "team1": "Cleveland Indians",
    "team2": "Los Angeles Dodgers",
    "year": 1991
  },
  {
    "player": "Brett Butler",
    "team1": "Cleveland Indians",
    "team2": "San Francisco Giants",
    "year": 1989
  },
  {
    "player": "Brett Butler",
    "team1": "Los Angeles Dodgers",
    "team2": "San Francisco Giants",
    "year": 1991
  },
  {
    "player": "Mark Davis",
    "team1": "Kansas City Royals",
    "team2": "San Diego Padres",
    "year": 1992
  },
  {
    "player": "Mark Davis",
    "team1": "Kansas City Royals",
    "team2": "San Francisco Giants",
    "year": 1992
  },
  {
    "player": "Mark Davis",
    "team1": "San Diego Padres",
    "team2": "San Francisco Giants",
    "year": 1990
  },
  {
    "player": "Bert Blyleven",
    "team1": "Anaheim Angels",
    "team2": "Cleveland Indians",
    "year": 1989
  },
  {
    "player": "Bert Blyleven",
    "team1": "Anaheim Angels",
    "team2": "Minnesota Twins",
    "year": 1989
  },
  {
    "player": "Bert Blyleven",
    "team1": "Cleveland Indians",
    "team2": "Minnesota Twins",
    "year": 1989
  },
  {
    "player": "Vance Law",
    "team1": "Chicago Cubs",
    "team2": "Chicago White Sox",
    "year": 1989
  },
  {
    "player": "Vance Law",
    "team1": "Chicago Cubs",
    "team2": "Montreal Expos",
    "year": 1989
  },
  {
    "player": "Vance Law",
    "team1": "Chicago White Sox",
    "team2": "Montreal Expos",
    "year": 1988
  },
  {
    "player": "Dave Von Ohlen",
    "team1": "Cleveland Indians",
    "team2": "Oakland Athletics",
    "year": 1987
  },
  {
    "player": "Jesse Orosco",
    "team1": "Cleveland Indians",
    "team2": "New York Mets",
    "year": 1992
  },
  {
    "player": "Storm Davis",
    "team1": "Baltimore Orioles",
    "team2": "Oakland Athletics",
    "year": 1990
  },
  {
    "player": "Jose Rijo",
    "team1": "Cincinnati Reds",
    "team2": "Oakland Athletics",
    "year": 1993
  },
  {
    "player": "Johnny Ray",
    "team1": "Anaheim Angels",
    "team2": "Pittsburgh Pirates",
    "year": 1991
  },
  {
    "player": "Don Aase",
    "team1": "Baltimore Orioles",
    "team2": "Los Angeles Dodgers",
    "year": 1991
  },
  {
    "player": "Don Aase",
    "team1": "Baltimore Orioles",
    "team2": "New York Mets",
    "year": 1991
  },
  {
    "player": "Don Aase",
    "team1": "Los Angeles Dodgers",
    "team2": "New York Mets",
    "year": 1991
  },
  {
    "player": "Jeff Reardon",
    "team1": "Boston Red Sox",
    "team2": "Minnesota Twins",
    "year": 1992
  },
  {
    "player": "Jeff Reardon",
    "team1": "Boston Red Sox",
    "team2": "Montreal Expos",
    "year": 1992
  },
  {
    "player": "Jeff Reardon",
    "team1": "Minnesota Twins",
    "team2": "Montreal Expos",
    "year": 1990
  },
  {
    "player": "Rick Rhoden",
    "team1": "Houston Astros",
    "team2": "New York Yankees",
    "year": 1990
  },
  {
    "player": "Rick Rhoden",
    "team1": "Houston Astros",
    "team2": "Pittsburgh Pirates",
    "year": 1990
  },
  {
    "player": "Rick Rhoden",
    "team1": "New York Yankees",
    "team2": "Pittsburgh Pirates",
    "year": 1989
  },
  {
    "player": "Kevin Bass",
    "team1": "Houston Astros",
    "team2": "San Francisco Giants",
    "year": 1992
  },
  {
    "player": "Scott Fletcher",
    "team1": "Chicago White Sox",
    "team2": "Texas Rangers",
    "year": 1991
  },
  {
    "player": "Steve Carlton",
    "team1": "Cleveland Indians",
    "team2": "San Francisco Giants",
    "year": 1987
  },
  {
    "player": "Mike Witt",
    "team1": "Anaheim Angels",
    "team2": "New York Yankees",
    "year": 1991
  },
  {
    "player": "Bill Gullickson",
    "team1": "Cincinnati Reds",
    "team2": "Detroit Tigers",
    "year": 1993
  },
  {
    "player": "Bill Gullickson",
    "team1": "Cincinnati Reds",
    "team2": "Houston Astros",
    "year": 1991
  },
  {
    "player": "Bill Gullickson",
    "team1": "Detroit Tigers",
    "team2": "Houston Astros",
    "year": 1993
  },
  {
    "player": "Dale Murphy",
    "team1": "Atlanta Braves",
    "team2": "Philadelphia Phillies",
    "year": 1992
  },
  {
    "player": "Bruce Hurst",
    "team1": "Boston Red Sox",
    "team2": "San Diego Padres",
    "year": 1993
  },
  {
    "player": "Steve Sax",
    "team1": "Chicago White Sox",
    "team2": "Los Angeles Dodgers",
    "year": 1992
  },
  {
    "player": "Steve Sax",
    "team1": "Chicago White Sox",
    "team2": "New York Yankees",
    "year": 1992
  },
  {
    "player": "Steve Sax",
    "team1": "Los Angeles Dodgers",
    "team2": "New York Yankees",
    "year": 1992
  },
  {
    "player": "John Cangelosi",
    "team1": "Chicago White Sox",
    "team2": "Pittsburgh Pirates",
    "year": 1989
  },
  {
    "player": "Dave Righetti",
    "team1": "New York Yankees",
    "team2": "San Francisco Giants",
    "year": 1992
  },
  {
    "player": "Lance Parrish",
    "team1": "Anaheim Angels",
    "team2": "Detroit Tigers",
    "year": 1992
  },
  {
    "player": "Lance Parrish",
    "team1": "Anaheim Angels",
    "team2": "Philadelphia Phillies",
    "year": 1992
  },
  {
    "player": "Lance Parrish",
    "team1": "Detroit Tigers",
    "team2": "Philadelphia Phillies",
    "year": 1989
  },
  {
    "player": "Ken Phelps",
    "team1": "New York Yankees",
    "team2": "Oakland Athletics",
    "year": 1990
  },
  {
    "player": "Ken Phelps",
    "team1": "New York Yankees",
    "team2": "Seattle Mariners",
    "year": 1989
  },
  {
    "player": "Ken Phelps",
    "team1": "Oakland Athletics",
    "team2": "Seattle Mariners",
    "year": 1990
  },
  {
    "player": "Billy Hatcher",
    "team1": "Chicago Cubs",
    "team2": "Cincinnati Reds",
    "year": 1992
  },
  {
    "player": "Billy Hatcher",
    "team1": "Chicago Cubs",
    "team2": "Houston Astros",
    "year": 1989
  },
  {
    "player": "Billy Hatcher",
    "team1": "Cincinnati Reds",
    "team2": "Houston Astros",
    "year": 1992
  },
  {
    "player": "Chris Brown",
    "team1": "San Diego Padres",
    "team2": "San Francisco Giants",
    "year": 1989
  },
  {
    "player": "Scott Sanderson",
    "team1": "Chicago Cubs",
    "team2": "New York Yankees",
    "year": 1992
  },
  {
    "player": "Scott Sanderson",
    "team1": "Chicago Cubs",
    "team2": "Oakland Athletics",
    "year": 1991
  },
  {
    "player": "Scott Sanderson",
    "team1": "New York Yankees",
    "team2": "Oakland Athletics",
    "year": 1992
  },
  {
    "player": "Wally Joyner",
    "team1": "Anaheim Angels",
    "team2": "Kansas City Royals",
    "year": 1993
  },
  {
    "player": "Wally Joyner",
    "team1": "Anaheim Angels",
    "team2": "San Diego Padres",
    "year": 1999
  },
  {
    "player": "Wally Joyner",
    "team1": "Kansas City Royals",
    "team2": "San Diego Padres",
    "year": 1999
  },
  {
    "player": "BJ Surhoff",
    "team1": "Baltimore Orioles",
    "team2": "Milwaukee Brewers",
    "year": 1999
  },
  {
    "player": "Randy Myers",
    "team1": "Baltimore Orioles",
    "team2": "New York Mets",
    "year": 1997
  },
  {
    "player": "Jerry Browne",
    "team1": "Cleveland Indians",
    "team2": "Oakland Athletics",
    "year": 1993
  },
  {
    "player": "Jerry Browne",
    "team1": "Cleveland Indians",
    "team2": "Texas Rangers",
    "year": 1989
  },
  {
    "player": "Jerry Browne",
    "team1": "Oakland Athletics",
    "team2": "Texas Rangers",
    "year": 1993
  },
  {
    "player": "Rick Dempsey",
    "team1": "Cleveland Indians",
    "team2": "Los Angeles Dodgers",
    "year": 1991
  },
  {
    "player": "Rick Dempsey",
    "team1": "Cleveland Indians",
    "team2": "Milwaukee Brewers",
    "year": 1991
  },
  {
    "player": "Rick Dempsey",
    "team1": "Los Angeles Dodgers",
    "team2": "Milwaukee Brewers",
    "year": 1991
  },
  {
    "player": "Gene Nelson",
    "team1": "Chicago White Sox",
    "team2": "Oakland Athletics",
    "year": 1991
  },
  {
    "player": "Dwight Evans",
    "team1": "Baltimore Orioles",
    "team2": "Boston Red Sox",
    "year": 1992
  },
  {
    "player": "Pete O'Brien",
    "team1": "Cleveland Indians",
    "team2": "Seattle Mariners",
    "year": 1992
  },
  {
    "player": "Pete O'Brien",
    "team1": "Cleveland Indians",
    "team2": "Texas Rangers",
    "year": 1990
  },
  {
    "player": "Pete O'Brien",
    "team1": "Seattle Mariners",
    "team2": "Texas Rangers",
    "year": 1992
  },
  {
    "player": "Tim Raines",
    "team1": "Chicago White Sox",
    "team2": "Montreal Expos",
    "year": 1993
  },
  {
    "player": "Andy Van Slyke",
    "team1": "Pittsburgh Pirates",
    "team2": "St. Louis Cardinals",
    "year": 1992
  },
  {
    "player": "John Morris",
    "team1": "Anaheim Angels",
    "team2": "St. Louis Cardinals",
    "year": 1992
  },
  {
    "player": "Sal Butera",
    "team1": "Cincinnati Reds",
    "team2": "Minnesota Twins",
    "year": 1988
  },
  {
    "player": "Scott Terry",
    "team1": "Cincinnati Reds",
    "team2": "St. Louis Cardinals",
    "year": 1992
  },
  {
    "player": "Dennis Eckersley",
    "team1": "Chicago Cubs",
    "team2": "Oakland Athletics",
    "year": 1991
  },
  {
    "player": "Carmen Castillo",
    "team1": "Cleveland Indians",
    "team2": "Minnesota Twins",
    "year": 1991
  },
  {
    "player": "Reid Nichols",
    "team1": "Chicago White Sox",
    "team2": "Montreal Expos",
    "year": 1988
  },
  {
    "player": "Zane Smith",
    "team1": "Atlanta Braves",
    "team2": "Montreal Expos",
    "year": 1990
  },
  {
    "player": "Zane Smith",
    "team1": "Atlanta Braves",
    "team2": "Pittsburgh Pirates",
    "year": 1992
  },
  {
    "player": "Zane Smith",
    "team1": "Montreal Expos",
    "team2": "Pittsburgh Pirates",
    "year": 1992
  },
  {
    "player": "John Cerutti",
    "team1": "Detroit Tigers",
    "team2": "Toronto Blue Jays",
    "year": 1991
  },
  {
    "player": "Jose Uribe",
    "team1": "Oakland Athletics",
    "team2": "San Francisco Giants",
    "year": 1991
  },
  {
    "player": "Mickey Tettleton",
    "team1": "Baltimore Orioles",
    "team2": "Detroit Tigers",
    "year": 1993
  },
  {
    "player": "Mickey Tettleton",
    "team1": "Baltimore Orioles",
    "team2": "Oakland Athletics",
    "year": 1989
  },
  {
    "player": "Mickey Tettleton",
    "team1": "Detroit Tigers",
    "team2": "Oakland Athletics",
    "year": 1993
  },
  {
    "player": "Mark McGwire",
    "team1": "Oakland Athletics",
    "team2": "St. Louis Cardinals",
    "year": 1999
  },
  {
    "player": "Kal Daniels",
    "team1": "Cincinnati Reds",
    "team2": "Los Angeles Dodgers",
    "year": 1990
  },
  {
    "player": "Gary Gaetti",
    "team1": "Anaheim Angels",
    "team2": "Minnesota Twins",
    "year": 1992
  },
  {
    "player": "Bob Welch",
    "team1": "Los Angeles Dodgers",
    "team2": "Oakland Athletics",
    "year": 1992
  },
  {
    "player": "Ivan Calderon",
    "team1": "Chicago White Sox",
    "team2": "Montreal Expos",
    "year": 1992
  },
  {
    "player": "Lance Johnson",
    "team1": "Chicago White Sox",
    "team2": "St. Louis Cardinals",
    "year": 1991
  },
  {
    "player": "Roberto Alomar",
    "team1": "Baltimore Orioles",
    "team2": "San Diego Padres",
    "year": 1999
  },
  {
    "player": "Roberto Alomar",
    "team1": "Baltimore Orioles",
    "team2": "Toronto Blue Jays",
    "year": 1999
  },
  {
    "player": "Roberto Alomar",
    "team1": "San Diego Padres",
    "team2": "Toronto Blue Jays",
    "year": 1992
  },
  {
    "player": "Shawn Hillegas",
    "team1": "Chicago White Sox",
    "team2": "Cleveland Indians",
    "year": 1991
  },
  {
    "player": "Shawn Hillegas",
    "team1": "Chicago White Sox",
    "team2": "Los Angeles Dodgers",
    "year": 1990
  },
  {
    "player": "Shawn Hillegas",
    "team1": "Cleveland Indians",
    "team2": "Los Angeles Dodgers",
    "year": 1991
  },
  {
    "player": "Roger Clemens",
    "team1": "Boston Red Sox",
    "team2": "Toronto Blue Jays",
    "year": 1999
  },
  {
    "player": "Jeff Reed",
    "team1": "Cincinnati Reds",
    "team2": "Montreal Expos",
    "year": 1991
  },
  {
    "player": "Jeff Reed",
    "team1": "Cincinnati Reds",
    "team2": "San Francisco Giants",
    "year": 1993
  },
  {
    "player": "Jeff Reed",
    "team1": "Montreal Expos",
    "team2": "San Francisco Giants",
    "year": 1993
  },
  {
    "player": "Ted Power",
    "team1": "Cincinnati Reds",
    "team2": "Kansas City Royals",
    "year": 1989
  },
  {
    "player": "Ted Power",
    "team1": "Cincinnati Reds",
    "team2": "Pittsburgh Pirates",
    "year": 1991
  },
  {
    "player": "Ted Power",
    "team1": "Cincinnati Reds",
    "team2": "Texas Rangers",
    "year": 1989
  },
  {
    "player": "Ted Power",
    "team1": "Kansas City Royals",
    "team2": "Pittsburgh Pirates",
    "year": 1991
  },
  {
    "player": "Ted Power",
    "team1": "Kansas City Royals",
    "team2": "Texas Rangers",
    "year": 1989
  },
  {
    "player": "Ted Power",
    "team1": "Pittsburgh Pirates",
    "team2": "Texas Rangers",
    "year": 1991
  },
  {
    "player": "Felix Fermin",
    "team1": "Cleveland Indians",
    "team2": "Pittsburgh Pirates",
    "year": 1990
  },
  {
    "player": "Frank Viola",
    "team1": "Minnesota Twins",
    "team2": "New York Mets",
    "year": 1992
  },
  {
    "player": "Terry Kennedy",
    "team1": "Baltimore Orioles",
    "team2": "San Francisco Giants",
    "year": 1991
  },
  {
    "player": "Matt Nokes",
    "team1": "Detroit Tigers",
    "team2": "New York Yankees",
    "year": 1992
  },
  {
    "player": "Mariano Duncan",
    "team1": "Cincinnati Reds",
    "team2": "Los Angeles Dodgers",
    "year": 1991
  },
  {
    "player": "Julio Franco",
    "team1": "Cleveland Indians",
    "team2": "Texas Rangers",
    "year": 1997
  },
  {
    "player": "Charlie Leibrandt",
    "team1": "Atlanta Braves",
    "team2": "Kansas City Royals",
    "year": 1993
  },
  {
    "player": "Ron Robinson",
    "team1": "Cincinnati Reds",
    "team2": "Milwaukee Brewers",
    "year": 1991
  },
  {
    "player": "Jamie Moyer",
    "team1": "Chicago Cubs",
    "team2": "St. Louis Cardinals",
    "year": 1991
  },
  {
    "player": "Jamie Moyer",
    "team1": "Chicago Cubs",
    "team2": "Texas Rangers",
    "year": 1989
  },
  {
    "player": "Jamie Moyer",
    "team1": "St. Louis Cardinals",
    "team2": "Texas Rangers",
    "year": 1991
  },
  {
    "player": "Tony Pena",
    "team1": "Boston Red Sox",
    "team2": "St. Louis Cardinals",
    "year": 1992
  },
  {
    "player": "Ellis Burks",
    "team1": "Boston Red Sox",
    "team2": "San Francisco Giants",
    "year": 1999
  },
  {
    "player": "Danny Tartabull",
    "team1": "Chicago White Sox",
    "team2": "Kansas City Royals",
    "year": 1997
  },
  {
    "player": "Danny Tartabull",
    "team1": "Chicago White Sox",
    "team2": "New York Yankees",
    "year": 1997
  },
  {
    "player": "Danny Tartabull",
    "team1": "Kansas City Royals",
    "team2": "New York Yankees",
    "year": 1993
  },
  {
    "player": "Casey Candaele",
    "team1": "Houston Astros",
    "team2": "Montreal Expos",
    "year": 1992
  },
  {
    "player": "Mark McLemore",
    "team1": "Anaheim Angels",
    "team2": "Texas Rangers",
    "year": 1999
  },
  {
    "player": "Jack Clark",
    "team1": "Boston Red Sox",
    "team2": "San Diego Padres",
    "year": 1992
  },
  {
    "player": "Jack Clark",
    "team1": "Boston Red Sox",
    "team2": "St. Louis Cardinals",
    "year": 1992
  },
  {
    "player": "Jack Clark",
    "team1": "San Diego Padres",
    "team2": "St. Louis Cardinals",
    "year": 1990
  },
  {
    "player": "Luis Aguayo",
    "team1": "Cleveland Indians",
    "team2": "New York Yankees",
    "year": 1989
  },
  {
    "player": "Luis Aguayo",
    "team1": "Cleveland Indians",
    "team2": "Philadelphia Phillies",
    "year": 1989
  },
  {
    "player": "Luis Aguayo",
    "team1": "New York Yankees",
    "team2": "Philadelphia Phillies",
    "year": 1989
  },
  {
    "player": "Stan Jefferson",
    "team1": "New York Yankees",
    "team2": "San Diego Padres",
    "year": 1989
  },
  {
    "player": "Sid Bream",
    "team1": "Atlanta Braves",
    "team2": "Pittsburgh Pirates",
    "year": 1992
  },
  {
    "player": "Fred McGriff",
    "team1": "San Diego Padres",
    "team2": "Tampa Bay Rays",
    "year": 1999
  },
  {
    "player": "Fred McGriff",
    "team1": "San Diego Padres",
    "team2": "Toronto Blue Jays",
    "year": 1992
  },
  {
    "player": "Fred McGriff",
    "team1": "Tampa Bay Rays",
    "team2": "Toronto Blue Jays",
    "year": 1999
  },
  {
    "player": "Steve Lombardozzi",
    "team1": "Houston Astros",
    "team2": "Minnesota Twins",
    "year": 1990
  },
  {
    "player": "Gary Carter",
    "team1": "Los Angeles Dodgers",
    "team2": "New York Mets",
    "year": 1991
  },
  {
    "player": "Gary Carter",
    "team1": "Los Angeles Dodgers",
    "team2": "San Francisco Giants",
    "year": 1991
  },
  {
    "player": "Gary Carter",
    "team1": "New York Mets",
    "team2": "San Francisco Giants",
    "year": 1991
  },
  {
    "player": "Ken Griffey Sr",
    "team1": "Atlanta Braves",
    "team2": "Cincinnati Reds",
    "year": 1989
  },
  {
    "player": "Ken Griffey Sr",
    "team1": "Atlanta Braves",
    "team2": "Los Angeles Dodgers",
    "year": 1991
  },
  {
    "player": "Ken Griffey Sr",
    "team1": "Atlanta Braves",
    "team2": "Seattle Mariners",
    "year": 1992
  },
  {
    "player": "Ken Griffey Sr",
    "team1": "Cincinnati Reds",
    "team2": "Los Angeles Dodgers",
    "year": 1991
  },
  {
    "player": "Ken Griffey Sr",
    "team1": "Cincinnati Reds",
    "team2": "Seattle Mariners",
    "year": 1992
  },
  {
    "player": "Ken Griffey Sr",
    "team1": "Los Angeles Dodgers",
    "team2": "Seattle Mariners",
    "year": 1992
  },
  {
    "player": "Tommy Gregg",
    "team1": "Atlanta Braves",
    "team2": "Pittsburgh Pirates",
    "year": 1989
  },
  {
    "player": "Will Clark",
    "team1": "San Francisco Giants",
    "team2": "Texas Rangers",
    "year": 1999
  },
  {
    "player": "John Kruk",
    "team1": "Philadelphia Phillies",
    "team2": "San Diego Padres",
    "year": 1991
  },
  {
    "player": "Gary Pettis",
    "team1": "Anaheim Angels",
    "team2": "Detroit Tigers",
    "year": 1989
  },
  {
    "player": "Gary Pettis",
    "team1": "Anaheim Angels",
    "team2": "Texas Rangers",
    "year": 1991
  },
  {
    "player": "Gary Pettis",
    "team1": "Detroit Tigers",
    "team2": "Texas Rangers",
    "year": 1991
  },
  {
    "player": "Harold Baines",
    "team1": "Chicago White Sox",
    "team2": "Oakland Athletics",
    "year": 1993
  },
  {
    "player": "Pat Tabler",
    "team1": "Cleveland Indians",
    "team2": "Kansas City Royals",
    "year": 1990
  },
  {
    "player": "Pat Tabler",
    "team1": "Cleveland Indians",
    "team2": "New York Mets",
    "year": 1991
  },
  {
    "player": "Pat Tabler",
    "team1": "Kansas City Royals",
    "team2": "New York Mets",
    "year": 1991
  },
  {
    "player": "Tony Phillips",
    "team1": "Chicago White Sox",
    "team2": "Detroit Tigers",
    "year": 1997
  },
  {
    "player": "Tony Phillips",
    "team1": "Chicago White Sox",
    "team2": "Oakland Athletics",
    "year": 1997
  },
  {
    "player": "Tony Phillips",
    "team1": "Detroit Tigers",
    "team2": "Oakland Athletics",
    "year": 1993
  },
  {
    "player": "Steve Buechele",
    "team1": "Pittsburgh Pirates",
    "team2": "Texas Rangers",
    "year": 1992
  },
  {
    "player": "Mike Marshall",
    "team1": "Boston Red Sox",
    "team2": "Los Angeles Dodgers",
    "year": 1991
  },
  {
    "player": "Bill Doran",
    "team1": "Cincinnati Reds",
    "team2": "Houston Astros",
    "year": 1991
  },
  {
    "player": "Milt Thompson",
    "team1": "Philadelphia Phillies",
    "team2": "St. Louis Cardinals",
    "year": 1990
  },
  {
    "player": "Marvell Wynne",
    "team1": "Chicago Cubs",
    "team2": "San Diego Padres",
    "year": 1991
  },
  {
    "player": "Glenn Braggs",
    "team1": "Cincinnati Reds",
    "team2": "Milwaukee Brewers",
    "year": 1992
  },
  {
    "player": "Wally Backman",
    "team1": "Minnesota Twins",
    "team2": "New York Mets",
    "year": 1989
  },
  {
    "player": "Wally Backman",
    "team1": "Minnesota Twins",
    "team2": "Pittsburgh Pirates",
    "year": 1991
  },
  {
    "player": "Wally Backman",
    "team1": "New York Mets",
    "team2": "Pittsburgh Pirates",
    "year": 1991
  },
  {
    "player": "Phil Bradley",
    "team1": "Chicago White Sox",
    "team2": "Philadelphia Phillies",
    "year": 1991
  },
  {
    "player": "Phil Bradley",
    "team1": "Chicago White Sox",
    "team2": "Seattle Mariners",
    "year": 1991
  },
  {
    "player": "Phil Bradley",
    "team1": "Philadelphia Phillies",
    "team2": "Seattle Mariners",
    "year": 1989
  },
  {
    "player": "Tom Brunansky",
    "team1": "Boston Red Sox",
    "team2": "Minnesota Twins",
    "year": 1991
  },
  {
    "player": "Tom Brunansky",
    "team1": "Boston Red Sox",
    "team2": "St. Louis Cardinals",
    "year": 1991
  },
  {
    "player": "Tom Brunansky",
    "team1": "Minnesota Twins",
    "team2": "St. Louis Cardinals",
    "year": 1989
  },
  {
    "player": "Fred Lynn",
    "team1": "Baltimore Orioles",
    "team2": "Detroit Tigers",
    "year": 1989
  },
  {
    "player": "Darrell Evans",
    "team1": "Atlanta Braves",
    "team2": "Detroit Tigers",
    "year": 1990
  },
  {
    "player": "Joe Carter",
    "team1": "Cleveland Indians",
    "team2": "San Diego Padres",
    "year": 1991
  },
  {
    "player": "Joe Carter",
    "team1": "Cleveland Indians",
    "team2": "Toronto Blue Jays",
    "year": 1991
  },
  {
    "player": "Joe Carter",
    "team1": "San Diego Padres",
    "team2": "Toronto Blue Jays",
    "year": 1991
  },
  {
    "player": "Willie Wilson",
    "team1": "Kansas City Royals",
    "team2": "Oakland Athletics",
    "year": 1993
  },
  {
    "player": "Mitch Webster",
    "team1": "Chicago Cubs",
    "team2": "Cleveland Indians",
    "year": 1990
  },
  {
    "player": "Mitch Webster",
    "team1": "Chicago Cubs",
    "team2": "Montreal Expos",
    "year": 1989
  },
  {
    "player": "Mitch Webster",
    "team1": "Cleveland Indians",
    "team2": "Montreal Expos",
    "year": 1990
  },
  {
    "player": "Brian Downing",
    "team1": "Anaheim Angels",
    "team2": "Texas Rangers",
    "year": 1992
  },
  {
    "player": "Mike Stanley",
    "team1": "New York Yankees",
    "team2": "Texas Rangers",
    "year": 1993
  },
  {
    "player": "Glenn Wilson",
    "team1": "Houston Astros",
    "team2": "Philadelphia Phillies",
    "year": 1990
  },
  {
    "player": "Kurt Stillwell",
    "team1": "Cincinnati Reds",
    "team2": "Kansas City Royals",
    "year": 1991
  },
  {
    "player": "Kurt Stillwell",
    "team1": "Cincinnati Reds",
    "team2": "San Diego Padres",
    "year": 1992
  },
  {
    "player": "Kurt Stillwell",
    "team1": "Kansas City Royals",
    "team2": "San Diego Padres",
    "year": 1992
  },
  {
    "player": "Lee Guetterman",
    "team1": "New York Yankees",
    "team2": "Seattle Mariners",
    "year": 1992
  },
  {
    "player": "Willie Upshaw",
    "team1": "Cleveland Indians",
    "team2": "Toronto Blue Jays",
    "year": 1988
  },
  {
    "player": "Rob Deer",
    "team1": "Detroit Tigers",
    "team2": "Milwaukee Brewers",
    "year": 1992
  },
  {
    "player": "Kirk Gibson",
    "team1": "Detroit Tigers",
    "team2": "Kansas City Royals",
    "year": 1995
  },
  {
    "player": "Kirk Gibson",
    "team1": "Detroit Tigers",
    "team2": "Los Angeles Dodgers",
    "year": 1995
  },
  {
    "player": "Kirk Gibson",
    "team1": "Kansas City Royals",
    "team2": "Los Angeles Dodgers",
    "year": 1992
  },
  {
    "player": "Pedro Guerrero",
    "team1": "Los Angeles Dodgers",
    "team2": "St. Louis Cardinals",
    "year": 1992
  },
  {
    "player": "Mike Davis",
    "team1": "Los Angeles Dodgers",
    "team2": "Oakland Athletics",
    "year": 1990
  },
  {
    "player": "Andres Galarraga",
    "team1": "Atlanta Braves",
    "team2": "Colorado Rockies",
    "year": 1999
  },
  {
    "player": "Andres Galarraga",
    "team1": "Atlanta Braves",
    "team2": "Montreal Expos",
    "year": 1999
  },
  {
    "player": "Andres Galarraga",
    "team1": "Colorado Rockies",
    "team2": "Montreal Expos",
    "year": 1996
  },
  {
    "player": "Juan Samuel",
    "team1": "Los Angeles Dodgers",
    "team2": "New York Mets",
    "year": 1992
  },
  {
    "player": "Juan Samuel",
    "team1": "Los Angeles Dodgers",
    "team2": "Philadelphia Phillies",
    "year": 1992
  },
  {
    "player": "Juan Samuel",
    "team1": "New York Mets",
    "team2": "Philadelphia Phillies",
    "year": 1990
  },
  {
    "player": "Tom Niedenfuer",
    "team1": "Baltimore Orioles",
    "team2": "Seattle Mariners",
    "year": 1989
  },
  {
    "player": "Jeff Robinson",
    "team1": "Baltimore Orioles",
    "team2": "Detroit Tigers",
    "year": 1992
  },
  {
    "player": "Jeff Robinson",
    "team1": "Baltimore Orioles",
    "team2": "New York Yankees",
    "year": 1992
  },
  {
    "player": "Jeff Robinson",
    "team1": "Baltimore Orioles",
    "team2": "Pittsburgh Pirates",
    "year": 1992
  },
  {
    "player": "Jeff Robinson",
    "team1": "Detroit Tigers",
    "team2": "New York Yankees",
    "year": 1991
  },
  {
    "player": "Jeff Robinson",
    "team1": "Detroit Tigers",
    "team2": "Pittsburgh Pirates",
    "year": 1991
  },
  {
    "player": "Jeff Robinson",
    "team1": "New York Yankees",
    "team2": "Pittsburgh Pirates",
    "year": 1991
  },
  {
    "player": "Todd Benzinger",
    "team1": "Boston Red Sox",
    "team2": "Cincinnati Reds",
    "year": 1990
  },
  {
    "player": "Dave Winfield",
    "team1": "Anaheim Angels",
    "team2": "New York Yankees",
    "year": 1991
  },
  {
    "player": "Bud Black",
    "team1": "Cleveland Indians",
    "team2": "Kansas City Royals",
    "year": 1989
  },
  {
    "player": "Bud Black",
    "team1": "Cleveland Indians",
    "team2": "San Francisco Giants",
    "year": 1991
  },
  {
    "player": "Bud Black",
    "team1": "Kansas City Royals",
    "team2": "San Francisco Giants",
    "year": 1991
  },
  {
    "player": "Jose Canseco",
    "team1": "Oakland Athletics",
    "team2": "Texas Rangers",
    "year": 1993
  },
  {
    "player": "Bob Boone",
    "team1": "Anaheim Angels",
    "team2": "Kansas City Royals",
    "year": 1989
  },
  {
    "player": "Willie McGee",
    "team1": "San Francisco Giants",
    "team2": "St. Louis Cardinals",
    "year": 1992
  },
  {
    "player": "Tracy Jones",
    "team1": "Cincinnati Reds",
    "team2": "Montreal Expos",
    "year": 1989
  },
  {
    "player": "Tracy Jones",
    "team1": "Cincinnati Reds",
    "team2": "Seattle Mariners",
    "year": 1992
  },
  {
    "player": "Tracy Jones",
    "team1": "Montreal Expos",
    "team2": "Seattle Mariners",
    "year": 1992
  },
  {
    "player": "Chili Davis",
    "team1": "Anaheim Angels",
    "team2": "Minnesota Twins",
    "year": 1992
  },
  {
    "player": "Chili Davis",
    "team1": "Anaheim Angels",
    "team2": "San Francisco Giants",
    "year": 1991
  },
  {
    "player": "Chili Davis",
    "team1": "Minnesota Twins",
    "team2": "San Francisco Giants",
    "year": 1992
  },
  {
    "player": "Keith Hernandez",
    "team1": "Cleveland Indians",
    "team2": "New York Mets",
    "year": 1991
  },
  {
    "player": "Mark Langston",
    "team1": "Anaheim Angels",
    "team2": "Seattle Mariners",
    "year": 1992
  },
  {
    "player": "Keith Atherton",
    "team1": "Cleveland Indians",
    "team2": "Minnesota Twins",
    "year": 1989
  },
  {
    "player": "Tony Fernandez",
    "team1": "San Diego Padres",
    "team2": "Toronto Blue Jays",
    "year": 1991
  },
  {
    "player": "Mike Kingery",
    "team1": "San Francisco Giants",
    "team2": "Seattle Mariners",
    "year": 1991
  },
  {
    "player": "Rafael Palmeiro",
    "team1": "Baltimore Orioles",
    "team2": "Chicago Cubs",
    "year": 1998
  },
  {
    "player": "Rafael Palmeiro",
    "team1": "Baltimore Orioles",
    "team2": "Texas Rangers",
    "year": 1998
  },
  {
    "player": "Rafael Palmeiro",
    "team1": "Chicago Cubs",
    "team2": "Texas Rangers",
    "year": 1992
  },
  {
    "player": "Barry Bonds",
    "team1": "Pittsburgh Pirates",
    "team2": "San Francisco Giants",
    "year": 1999
  },
  {
    "player": "Jeffrey Leonard",
    "team1": "Milwaukee Brewers",
    "team2": "San Francisco Giants",
    "year": 1989
  },
  {
    "player": "Jeffrey Leonard",
    "team1": "Milwaukee Brewers",
    "team2": "Seattle Mariners",
    "year": 1991
  },
  {
    "player": "Jeffrey Leonard",
    "team1": "San Francisco Giants",
    "team2": "Seattle Mariners",
    "year": 1991
  },
  {
    "player": "Ken Williams",
    "team1": "Chicago White Sox",
    "team2": "Toronto Blue Jays",
    "year": 1991
  },
  {
    "player": "Bryn Smith",
    "team1": "Montreal Expos",
    "team2": "St. Louis Cardinals",
    "year": 1992
  },
  {
    "player": "Rick Cerone",
    "team1": "Boston Red Sox",
    "team2": "New York Yankees",
    "year": 1991
  },
  {
    "player": "John Shelby",
    "team1": "Detroit Tigers",
    "team2": "Los Angeles Dodgers",
    "year": 1991
  },
  {
    "player": "Alex Trevino",
    "team1": "Houston Astros",
    "team2": "Los Angeles Dodgers",
    "year": 1989
  },
  {
    "player": "Rick Schu",
    "team1": "Baltimore Orioles",
    "team2": "Detroit Tigers",
    "year": 1990
  },
  {
    "player": "Rick Schu",
    "team1": "Baltimore Orioles",
    "team2": "Philadelphia Phillies",
    "year": 1989
  },
  {
    "player": "Rick Schu",
    "team1": "Detroit Tigers",
    "team2": "Philadelphia Phillies",
    "year": 1990
  },
  {
    "player": "Paul O'Neill",
    "team1": "Cincinnati Reds",
    "team2": "New York Yankees",
    "year": 1999
  },
  {
    "player": "Gerald Perry",
    "team1": "Atlanta Braves",
    "team2": "Kansas City Royals",
    "year": 1991
  },
  {
    "player": "Gerald Perry",
    "team1": "Atlanta Braves",
    "team2": "St. Louis Cardinals",
    "year": 1992
  },
  {
    "player": "Gerald Perry",
    "team1": "Kansas City Royals",
    "team2": "St. Louis Cardinals",
    "year": 1992
  },
  {
    "player": "Dave Martinez",
    "team1": "Chicago Cubs",
    "team2": "Cincinnati Reds",
    "year": 1993
  },
  {
    "player": "Dave Martinez",
    "team1": "Chicago Cubs",
    "team2": "Montreal Expos",
    "year": 1992
  },
  {
    "player": "Dave Martinez",
    "team1": "Cincinnati Reds",
    "team2": "Montreal Expos",
    "year": 1993
  },
  {
    "player": "Darryl Strawberry",
    "team1": "Los Angeles Dodgers",
    "team2": "New York Mets",
    "year": 1993
  },
  {
    "player": "Darryl Strawberry",
    "team1": "Los Angeles Dodgers",
    "team2": "New York Yankees",
    "year": 1999
  },
  {
    "player": "Darryl Strawberry",
    "team1": "New York Mets",
    "team2": "New York Yankees",
    "year": 1999
  },
  {
    "player": "John Moses",
    "team1": "Minnesota Twins",
    "team2": "Seattle Mariners",
    "year": 1991
  },
  {
    "player": "Greg Gagne",
    "team1": "Los Angeles Dodgers",
    "team2": "Minnesota Twins",
    "year": 1995
  },
  {
    "player": "Jesse Barfield",
    "team1": "New York Yankees",
    "team2": "Toronto Blue Jays",
    "year": 1992
  },
  {
    "player": "Ed Nunez",
    "team1": "Seattle Mariners",
    "team2": "Texas Rangers",
    "year": 1993
  },
  {
    "player": "Rafael Ramirez",
    "team1": "Atlanta Braves",
    "team2": "Houston Astros",
    "year": 1991
  },
  {
    "player": "John Smiley",
    "team1": "Cleveland Indians",
    "team2": "Pittsburgh Pirates",
    "year": 1998
  },
  {
    "player": "Chris James",
    "team1": "Cleveland Indians",
    "team2": "Philadelphia Phillies",
    "year": 1992
  },
  {
    "player": "Terry Pendleton",
    "team1": "Atlanta Braves",
    "team2": "St. Louis Cardinals",
    "year": 1992
  },
  {
    "player": "Bill Buckner",
    "team1": "Anaheim Angels",
    "team2": "Kansas City Royals",
    "year": 1990
  },
  {
    "player": "Dan Pasqua",
    "team1": "Chicago White Sox",
    "team2": "New York Yankees",
    "year": 1993
  },
  {
    "player": "Paul Kilgus",
    "team1": "Chicago Cubs",
    "team2": "Texas Rangers",
    "year": 1990
  },
  {
    "player": "Dave Clark",
    "team1": "Chicago Cubs",
    "team2": "Cleveland Indians",
    "year": 1991
  },
  {
    "player": "Joel Skinner",
    "team1": "Cleveland Indians",
    "team2": "New York Yankees",
    "year": 1992
  },
  {
    "player": "Dan Petry",
    "team1": "Anaheim Angels",
    "team2": "Detroit Tigers",
    "year": 1991
  },
  {
    "player": "Carl Nichols",
    "team1": "Baltimore Orioles",
    "team2": "Houston Astros",
    "year": 1991
  },
  {
    "player": "Ernie Riles",
    "team1": "Milwaukee Brewers",
    "team2": "Oakland Athletics",
    "year": 1991
  },
  {
    "player": "Ernie Riles",
    "team1": "Milwaukee Brewers",
    "team2": "San Francisco Giants",
    "year": 1990
  },
  {
    "player": "Ernie Riles",
    "team1": "Oakland Athletics",
    "team2": "San Francisco Giants",
    "year": 1991
  },
  {
    "player": "Mike Bielecki",
    "team1": "Chicago Cubs",
    "team2": "Pittsburgh Pirates",
    "year": 1990
  },
  {
    "player": "Dan Gladden",
    "team1": "Detroit Tigers",
    "team2": "Minnesota Twins",
    "year": 1992
  },
  {
    "player": "Fred Manrique",
    "team1": "Chicago White Sox",
    "team2": "Minnesota Twins",
    "year": 1990
  },
  {
    "player": "Fred Manrique",
    "team1": "Chicago White Sox",
    "team2": "Texas Rangers",
    "year": 1990
  },
  {
    "player": "Fred Manrique",
    "team1": "Minnesota Twins",
    "team2": "Texas Rangers",
    "year": 1990
  },
  {
    "player": "Joe Hesketh",
    "team1": "Atlanta Braves",
    "team2": "Boston Red Sox",
    "year": 1992
  },
  {
    "player": "Joe Hesketh",
    "team1": "Atlanta Braves",
    "team2": "Montreal Expos",
    "year": 1990
  },
  {
    "player": "Joe Hesketh",
    "team1": "Boston Red Sox",
    "team2": "Montreal Expos",
    "year": 1992
  },
  {
    "player": "Gregg Jefferies",
    "team1": "Kansas City Royals",
    "team2": "New York Mets",
    "year": 1993
  },
  {
    "player": "Gregg Jefferies",
    "team1": "Kansas City Royals",
    "team2": "Philadelphia Phillies",
    "year": 1996
  },
  {
    "player": "Gregg Jefferies",
    "team1": "New York Mets",
    "team2": "Philadelphia Phillies",
    "year": 1996
  },
  {
    "player": "Andy Allanson",
    "team1": "Cleveland Indians",
    "team2": "Detroit Tigers",
    "year": 1992
  },
  {
    "player": "Domingo Ramos",
    "team1": "Chicago Cubs",
    "team2": "Cleveland Indians",
    "year": 1991
  },
  {
    "player": "Nolan Ryan",
    "team1": "Houston Astros",
    "team2": "Texas Rangers",
    "year": 1991
  },
  {
    "player": "Darnell Coles",
    "team1": "Pittsburgh Pirates",
    "team2": "Seattle Mariners",
    "year": 1990
  },
  {
    "player": "Curt Wilkerson",
    "team1": "Chicago Cubs",
    "team2": "Kansas City Royals",
    "year": 1993
  },
  {
    "player": "Curt Wilkerson",
    "team1": "Chicago Cubs",
    "team2": "Texas Rangers",
    "year": 1990
  },
  {
    "player": "Curt Wilkerson",
    "team1": "Kansas City Royals",
    "team2": "Texas Rangers",
    "year": 1993
  },
  {
    "player": "Ken Oberkfell",
    "team1": "Atlanta Braves",
    "team2": "Pittsburgh Pirates",
    "year": 1990
  },
  {
    "player": "Ken Oberkfell",
    "team1": "Atlanta Braves",
    "team2": "San Francisco Giants",
    "year": 1990
  },
  {
    "player": "Ken Oberkfell",
    "team1": "Pittsburgh Pirates",
    "team2": "San Francisco Giants",
    "year": 1990
  },
  {
    "player": "Donell Nixon",
    "team1": "San Francisco Giants",
    "team2": "Seattle Mariners",
    "year": 1990
  },
  {
    "player": "Bob Knepper",
    "team1": "Houston Astros",
    "team2": "San Francisco Giants",
    "year": 1990
  },
  {
    "player": "David Cone",
    "team1": "New York Mets",
    "team2": "New York Yankees",
    "year": 1999
  },
  {
    "player": "David Cone",
    "team1": "New York Mets",
    "team2": "Toronto Blue Jays",
    "year": 1993
  },
  {
    "player": "David Cone",
    "team1": "New York Yankees",
    "team2": "Toronto Blue Jays",
    "year": 1999
  },
  {
    "player": "Jerry Reuss",
    "team1": "Anaheim Angels",
    "team2": "Chicago White Sox",
    "year": 1989
  },
  {
    "player": "Jim Presley",
    "team1": "Atlanta Braves",
    "team2": "Seattle Mariners",
    "year": 1991
  },
  {
    "player": "Dave Parker",
    "team1": "Cincinnati Reds",
    "team2": "Oakland Athletics",
    "year": 1990
  },
  {
    "player": "Rick Leach",
    "team1": "Texas Rangers",
    "team2": "Toronto Blue Jays",
    "year": 1990
  },
  {
    "player": "Greg Harris",
    "team1": "Boston Red Sox",
    "team2": "San Diego Padres",
    "year": 1992
  },
  {
    "player": "Greg Harris",
    "team1": "Boston Red Sox",
    "team2": "Texas Rangers",
    "year": 1992
  },
  {
    "player": "Greg Harris",
    "team1": "San Diego Padres",
    "team2": "Texas Rangers",
    "year": 1992
  },
  {
    "player": "Matt Williams",
    "team1": "Cleveland Indians",
    "team2": "San Francisco Giants",
    "year": 1998
  },
  {
    "player": "Ron Hassey",
    "team1": "Chicago White Sox",
    "team2": "Oakland Athletics",
    "year": 1991
  },
  {
    "player": "Danny Gladden",
    "team1": "Detroit Tigers",
    "team2": "Minnesota Twins",
    "year": 1993
  },
  {
    "player": "Lloyd Moseby",
    "team1": "Detroit Tigers",
    "team2": "Toronto Blue Jays",
    "year": 1992
  },
  {
    "player": "Curt Ford",
    "team1": "Philadelphia Phillies",
    "team2": "St. Louis Cardinals",
    "year": 1990
  },
  {
    "player": "Oddibe McDowell",
    "team1": "Cleveland Indians",
    "team2": "Texas Rangers",
    "year": 1989
  },
  {
    "player": "Steve Shields",
    "team1": "New York Yankees",
    "team2": "Seattle Mariners",
    "year": 1989
  },
  {
    "player": "Jose DeLeon",
    "team1": "Chicago White Sox",
    "team2": "St. Louis Cardinals",
    "year": 1989
  },
  {
    "player": "Gary Redus",
    "team1": "Chicago White Sox",
    "team2": "Pittsburgh Pirates",
    "year": 1992
  },
  {
    "player": "Luis Quinones",
    "team1": "Chicago Cubs",
    "team2": "Cincinnati Reds",
    "year": 1992
  },
  {
    "player": "Jay Howell",
    "team1": "Los Angeles Dodgers",
    "team2": "Oakland Athletics",
    "year": 1992
  },
  {
    "player": "Mike Felder",
    "team1": "Milwaukee Brewers",
    "team2": "San Francisco Giants",
    "year": 1992
  },
  {
    "player": "Neal Heaton",
    "team1": "Montreal Expos",
    "team2": "Pittsburgh Pirates",
    "year": 1992
  },
  {
    "player": "Lonnie Smith",
    "team1": "Atlanta Braves",
    "team2": "Kansas City Royals",
    "year": 1990
  },
  {
    "player": "Joe Price",
    "team1": "Baltimore Orioles",
    "team2": "San Francisco Giants",
    "year": 1991
  },
  {
    "player": "John Tudor",
    "team1": "Los Angeles Dodgers",
    "team2": "St. Louis Cardinals",
    "year": 1989
  },
  {
    "player": "Ron Kittle",
    "team1": "Baltimore Orioles",
    "team2": "Chicago White Sox",
    "year": 1991
  },
  {
    "player": "Ron Kittle",
    "team1": "Baltimore Orioles",
    "team2": "Cleveland Indians",
    "year": 1991
  },
  {
    "player": "Ron Kittle",
    "team1": "Chicago White Sox",
    "team2": "Cleveland Indians",
    "year": 1989
  },
  {
    "player": "Brian Holton",
    "team1": "Baltimore Orioles",
    "team2": "Los Angeles Dodgers",
    "year": 1990
  },
  {
    "player": "Dave Schmidt",
    "team1": "Baltimore Orioles",
    "team2": "Montreal Expos",
    "year": 1991
  },
  {
    "player": "Mike Boddicker",
    "team1": "Boston Red Sox",
    "team2": "Kansas City Royals",
    "year": 1992
  },
  {
    "player": "Rob Murphy",
    "team1": "Boston Red Sox",
    "team2": "Cincinnati Reds",
    "year": 1991
  },
  {
    "player": "Rich Gedman",
    "team1": "Boston Red Sox",
    "team2": "St. Louis Cardinals",
    "year": 1992
  },
  {
    "player": "Kirk McCaskill",
    "team1": "Anaheim Angels",
    "team2": "Chicago White Sox",
    "year": 1992
  },
  {
    "player": "Bob McClure",
    "team1": "Anaheim Angels",
    "team2": "New York Mets",
    "year": 1989
  },
  {
    "player": "Bill Schroeder",
    "team1": "Anaheim Angels",
    "team2": "Milwaukee Brewers",
    "year": 1990
  },
  {
    "player": "Claudell Washington",
    "team1": "Anaheim Angels",
    "team2": "New York Yankees",
    "year": 1990
  },
  {
    "player": "Devon White",
    "team1": "Anaheim Angels",
    "team2": "Toronto Blue Jays",
    "year": 1991
  },
  {
    "player": "Jack McDowell",
    "team1": "Chicago White Sox",
    "team2": "New York Yankees",
    "year": 1996
  },
  {
    "player": "Bret Saberhagen",
    "team1": "Boston Red Sox",
    "team2": "Kansas City Royals",
    "year": 2000
  },
  {
    "player": "Bret Saberhagen",
    "team1": "Boston Red Sox",
    "team2": "New York Mets",
    "year": 2000
  },
  {
    "player": "Bret Saberhagen",
    "team1": "Kansas City Royals",
    "team2": "New York Mets",
    "year": 1993
  },
  {
    "player": "Gary Sheffield",
    "team1": "Florida Marlins",
    "team2": "Milwaukee Brewers",
    "year": 1996
  },
  {
    "player": "Juan Berenguer",
    "team1": "Atlanta Braves",
    "team2": "Minnesota Twins",
    "year": 1992
  },
  {
    "player": "Andy Hawkins",
    "team1": "New York Yankees",
    "team2": "San Diego Padres",
    "year": 1991
  },
  {
    "player": "Lance McCullers",
    "team1": "Detroit Tigers",
    "team2": "New York Yankees",
    "year": 1991
  },
  {
    "player": "Jimmy Jones",
    "team1": "Houston Astros",
    "team2": "New York Yankees",
    "year": 1992
  },
  {
    "player": "Jimmy Jones",
    "team1": "Houston Astros",
    "team2": "San Diego Padres",
    "year": 1992
  },
  {
    "player": "Jimmy Jones",
    "team1": "New York Yankees",
    "team2": "San Diego Padres",
    "year": 1991
  },
  {
    "player": "Bob Brower",
    "team1": "New York Yankees",
    "team2": "Texas Rangers",
    "year": 1989
  },
  {
    "player": "Mike Moore",
    "team1": "Oakland Athletics",
    "team2": "Seattle Mariners",
    "year": 1991
  },
  {
    "player": "Charlie Hough",
    "team1": "Chicago White Sox",
    "team2": "Florida Marlins",
    "year": 1993
  },
  {
    "player": "Charlie Hough",
    "team1": "Chicago White Sox",
    "team2": "Texas Rangers",
    "year": 1991
  },
  {
    "player": "Charlie Hough",
    "team1": "Florida Marlins",
    "team2": "Texas Rangers",
    "year": 1993
  },
  {
    "player": "Jeff Musselman",
    "team1": "New York Mets",
    "team2": "Toronto Blue Jays",
    "year": 1990
  },
  {
    "player": "Tony Castillo",
    "team1": "Atlanta Braves",
    "team2": "New York Mets",
    "year": 1992
  },
  {
    "player": "Tony Castillo",
    "team1": "Atlanta Braves",
    "team2": "Toronto Blue Jays",
    "year": 1990
  },
  {
    "player": "Tony Castillo",
    "team1": "New York Mets",
    "team2": "Toronto Blue Jays",
    "year": 1992
  },
  {
    "player": "Greg Maddux",
    "team1": "Atlanta Braves",
    "team2": "Chicago Cubs",
    "year": 1999
  },
  {
    "player": "Damon Berryhill",
    "team1": "Atlanta Braves",
    "team2": "Chicago Cubs",
    "year": 1993
  },
  {
    "player": "John Franco",
    "team1": "Cincinnati Reds",
    "team2": "New York Mets",
    "year": 1991
  },
  {
    "player": "Joel Youngblood",
    "team1": "Cincinnati Reds",
    "team2": "San Francisco Giants",
    "year": 1989
  },
  {
    "player": "Tim Belcher",
    "team1": "Anaheim Angels",
    "team2": "Cincinnati Reds",
    "year": 1999
  },
  {
    "player": "Tim Belcher",
    "team1": "Anaheim Angels",
    "team2": "Los Angeles Dodgers",
    "year": 1999
  },
  {
    "player": "Tim Belcher",
    "team1": "Cincinnati Reds",
    "team2": "Los Angeles Dodgers",
    "year": 1992
  },
  {
    "player": "Ricky Horton",
    "team1": "Los Angeles Dodgers",
    "team2": "St. Louis Cardinals",
    "year": 1990
  },
  {
    "player": "Tim Leary",
    "team1": "Cincinnati Reds",
    "team2": "Los Angeles Dodgers",
    "year": 1990
  },
  {
    "player": "Tim Leary",
    "team1": "Cincinnati Reds",
    "team2": "New York Yankees",
    "year": 1991
  },
  {
    "player": "Tim Leary",
    "team1": "Los Angeles Dodgers",
    "team2": "New York Yankees",
    "year": 1991
  },
  {
    "player": "Tim Burke",
    "team1": "Montreal Expos",
    "team2": "New York Mets",
    "year": 1992
  },
  {
    "player": "Sid Fernandez",
    "team1": "Los Angeles Dodgers",
    "team2": "New York Mets",
    "year": 1991
  },
  {
    "player": "Keith Miller",
    "team1": "New York Mets",
    "team2": "Philadelphia Phillies",
    "year": 1992
  },
  {
    "player": "Tim Teufel",
    "team1": "New York Mets",
    "team2": "San Diego Padres",
    "year": 1992
  },
  {
    "player": "Mookie Wilson",
    "team1": "New York Mets",
    "team2": "Toronto Blue Jays",
    "year": 1991
  },
  {
    "player": "Ken Dayley",
    "team1": "St. Louis Cardinals",
    "team2": "Toronto Blue Jays",
    "year": 1992
  },
  {
    "player": "Vince Coleman",
    "team1": "New York Mets",
    "team2": "Seattle Mariners",
    "year": 1996
  },
  {
    "player": "Vince Coleman",
    "team1": "New York Mets",
    "team2": "St. Louis Cardinals",
    "year": 1993
  },
  {
    "player": "Vince Coleman",
    "team1": "Seattle Mariners",
    "team2": "St. Louis Cardinals",
    "year": 1996
  },
  {
    "player": "Craig Lefferts",
    "team1": "San Diego Padres",
    "team2": "San Francisco Giants",
    "year": 1992
  },
  {
    "player": "Candy Maldonado",
    "team1": "Cleveland Indians",
    "team2": "San Francisco Giants",
    "year": 1991
  },
  {
    "player": "Candy Maldonado",
    "team1": "Cleveland Indians",
    "team2": "Toronto Blue Jays",
    "year": 1992
  },
  {
    "player": "Candy Maldonado",
    "team1": "San Francisco Giants",
    "team2": "Toronto Blue Jays",
    "year": 1992
  },
  {
    "player": "Dave West",
    "team1": "Minnesota Twins",
    "team2": "New York Mets",
    "year": 1992
  },
  {
    "player": "Steve Balboni",
    "team1": "New York Yankees",
    "team2": "Seattle Mariners",
    "year": 1990
  },
  {
    "player": "George Bell",
    "team1": "Chicago White Sox",
    "team2": "Toronto Blue Jays",
    "year": 1993
  },
  {
    "player": "Daryl Boston",
    "team1": "Chicago White Sox",
    "team2": "New York Mets",
    "year": 1992
  },
  {
    "player": "Jack Armstrong",
    "team1": "Cincinnati Reds",
    "team2": "Cleveland Indians",
    "year": 1992
  },
  {
    "player": "Lloyd McClendon",
    "team1": "Chicago Cubs",
    "team2": "Cincinnati Reds",
    "year": 1990
  },
  {
    "player": "Mike Devereaux",
    "team1": "Baltimore Orioles",
    "team2": "Los Angeles Dodgers",
    "year": 1991
  },
  {
    "player": "Barry Jones",
    "team1": "Chicago White Sox",
    "team2": "Montreal Expos",
    "year": 1992
  },
  {
    "player": "Mike Roesler",
    "team1": "Cincinnati Reds",
    "team2": "Nashville Sounds",
    "year": 1990
  },
  {
    "player": "Eddie Murray",
    "team1": "Baltimore Orioles",
    "team2": "Los Angeles Dodgers",
    "year": 1991
  },
  {
    "player": "Eddie Murray",
    "team1": "Baltimore Orioles",
    "team2": "New York Mets",
    "year": 1993
  },
  {
    "player": "Eddie Murray",
    "team1": "Los Angeles Dodgers",
    "team2": "New York Mets",
    "year": 1993
  },
  {
    "player": "Dickie Thon",
    "team1": "Philadelphia Phillies",
    "team2": "San Diego Padres",
    "year": 1990
  },
  {
    "player": "Dennis Boyd",
    "team1": "Boston Red Sox",
    "team2": "Montreal Expos",
    "year": 1991
  },
  {
    "player": "John Candelaria",
    "team1": "Los Angeles Dodgers",
    "team2": "Montreal Expos",
    "year": 1993
  },
  {
    "player": "John Candelaria",
    "team1": "Los Angeles Dodgers",
    "team2": "New York Yankees",
    "year": 1993
  },
  {
    "player": "John Candelaria",
    "team1": "Montreal Expos",
    "team2": "New York Yankees",
    "year": 1990
  },
  {
    "player": "Mike Jackson",
    "team1": "Cleveland Indians",
    "team2": "Seattle Mariners",
    "year": 1998
  },
  {
    "player": "Jeff Parrett",
    "team1": "Atlanta Braves",
    "team2": "Montreal Expos",
    "year": 1991
  },
  {
    "player": "Jeff Parrett",
    "team1": "Atlanta Braves",
    "team2": "Oakland Athletics",
    "year": 1993
  },
  {
    "player": "Jeff Parrett",
    "team1": "Montreal Expos",
    "team2": "Oakland Athletics",
    "year": 1993
  },
  {
    "player": "Mark Grant",
    "team1": "Atlanta Braves",
    "team2": "San Diego Padres",
    "year": 1991
  },
  {
    "player": "Mike Pagliarulo",
    "team1": "New York Yankees",
    "team2": "San Diego Padres",
    "year": 1991
  },
  {
    "player": "Eric King",
    "team1": "Chicago White Sox",
    "team2": "Cleveland Indians",
    "year": 1991
  },
  {
    "player": "Eric King",
    "team1": "Chicago White Sox",
    "team2": "Detroit Tigers",
    "year": 1991
  },
  {
    "player": "Eric King",
    "team1": "Cleveland Indians",
    "team2": "Detroit Tigers",
    "year": 1991
  },
  {
    "player": "Rick Aguilera",
    "team1": "Minnesota Twins",
    "team2": "New York Mets",
    "year": 1991
  },
  {
    "player": "Mark Eichhorn",
    "team1": "Anaheim Angels",
    "team2": "Toronto Blue Jays",
    "year": 1991
  },
  {
    "player": "Andy McGaffigan",
    "team1": "Kansas City Royals",
    "team2": "Montreal Expos",
    "year": 1991
  },
  {
    "player": "Darrin Jackson",
    "team1": "Chicago Cubs",
    "team2": "San Diego Padres",
    "year": 1993
  },
  {
    "player": "Bob Melvin",
    "team1": "Baltimore Orioles",
    "team2": "San Francisco Giants",
    "year": 1992
  },
  {
    "player": "Calvin Schiraldi",
    "team1": "Chicago Cubs",
    "team2": "San Diego Padres",
    "year": 1991
  },
  {
    "player": "Herm Winningham",
    "team1": "Boston Red Sox",
    "team2": "Cincinnati Reds",
    "year": 1993
  },
  {
    "player": "Luis Polonia",
    "team1": "Anaheim Angels",
    "team2": "Oakland Athletics",
    "year": 1993
  },
  {
    "player": "Chad Kreuter",
    "team1": "Detroit Tigers",
    "team2": "Texas Rangers",
    "year": 1993
  },
  {
    "player": "Mark Davidson",
    "team1": "Houston Astros",
    "team2": "Minnesota Twins",
    "year": 1991
  },
  {
    "player": "Paul Assenmacher",
    "team1": "Atlanta Braves",
    "team2": "Chicago Cubs",
    "year": 1990
  },
  {
    "player": "Nick Esasky",
    "team1": "Atlanta Braves",
    "team2": "Cincinnati Reds",
    "year": 1991
  },
  {
    "player": "Rock Raines",
    "team1": "Chicago White Sox",
    "team2": "Montreal Expos",
    "year": 1992
  },
  {
    "player": "Joe Boever",
    "team1": "Atlanta Braves",
    "team2": "Philadelphia Phillies",
    "year": 1992
  },
  {
    "player": "Drew Hall",
    "team1": "Chicago Cubs",
    "team2": "Montreal Expos",
    "year": 1991
  },
  {
    "player": "Jack Morris",
    "team1": "Detroit Tigers",
    "team2": "Minnesota Twins",
    "year": 1991
  },
  {
    "player": "Sandy Alomar, Jr",
    "team1": "Cleveland Indians",
    "team2": "San Diego Padres",
    "year": 1999
  },
  {
    "player": "Otis Nixon",
    "team1": "Atlanta Braves",
    "team2": "Montreal Expos",
    "year": 1992
  },
  {
    "player": "Dave Johnson",
    "team1": "Baltimore Orioles",
    "team2": "New York Mets",
    "year": 1992
  },
  {
    "player": "Jeff Treadway",
    "team1": "Atlanta Braves",
    "team2": "Cincinnati Reds",
    "year": 1992
  },
  {
    "player": "Dante Bichette",
    "team1": "Anaheim Angels",
    "team2": "Colorado Rockies",
    "year": 1999
  },
  {
    "player": "Dante Bichette",
    "team1": "Anaheim Angels",
    "team2": "Milwaukee Brewers",
    "year": 1992
  },
  {
    "player": "Dante Bichette",
    "team1": "Colorado Rockies",
    "team2": "Milwaukee Brewers",
    "year": 1999
  },
  {
    "player": "Ron Gant",
    "team1": "Atlanta Braves",
    "team2": "St. Louis Cardinals",
    "year": 1999
  },
  {
    "player": "Al Leiter",
    "team1": "New York Mets",
    "team2": "New York Yankees",
    "year": 1999
  },
  {
    "player": "Al Leiter",
    "team1": "New York Mets",
    "team2": "Toronto Blue Jays",
    "year": 1999
  },
  {
    "player": "Al Leiter",
    "team1": "New York Yankees",
    "team2": "Toronto Blue Jays",
    "year": 1990
  },
  {
    "player": "Scott Ruskin",
    "team1": "Montreal Expos",
    "team2": "Pittsburgh Pirates",
    "year": 1992
  },
  {
    "player": "Sammy Sosa",
    "team1": "Chicago Cubs",
    "team2": "Chicago White Sox",
    "year": 1999
  },
  {
    "player": "Walt Weiss",
    "team1": "Atlanta Braves",
    "team2": "Oakland Athletics",
    "year": 1999
  },
  {
    "player": "Kevin Gross",
    "team1": "Los Angeles Dodgers",
    "team2": "Montreal Expos",
    "year": 1993
  },
  {
    "player": "Don Slaught",
    "team1": "New York Yankees",
    "team2": "Pittsburgh Pirates",
    "year": 1991
  },
  {
    "player": "Tom Gordon",
    "team1": "Boston Red Sox",
    "team2": "Kansas City Royals",
    "year": 1999
  },
  {
    "player": "Walt Terrell",
    "team1": "Detroit Tigers",
    "team2": "New York Yankees",
    "year": 1992
  },
  {
    "player": "Steve Farr",
    "team1": "Kansas City Royals",
    "team2": "New York Yankees",
    "year": 1993
  },
  {
    "player": "Albert Belle",
    "team1": "Baltimore Orioles",
    "team2": "Cleveland Indians",
    "year": 1999
  },
  {
    "player": "Ken Hill",
    "team1": "Cleveland Indians",
    "team2": "Montreal Expos",
    "year": 1996
  },
  {
    "player": "Ken Hill",
    "team1": "Cleveland Indians",
    "team2": "St. Louis Cardinals",
    "year": 1996
  },
  {
    "player": "Ken Hill",
    "team1": "Montreal Expos",
    "team2": "St. Louis Cardinals",
    "year": 1993
  },
  {
    "player": "Scott Bailes",
    "team1": "Anaheim Angels",
    "team2": "Cleveland Indians",
    "year": 1992
  },
  {
    "player": "Omar Vizquel",
    "team1": "Cleveland Indians",
    "team2": "Seattle Mariners",
    "year": 1999
  },
  {
    "player": "Dave Anderson",
    "team1": "Los Angeles Dodgers",
    "team2": "San Francisco Giants",
    "year": 1991
  },
  {
    "player": "Jay Bell",
    "team1": "Arizona Diamondbacks",
    "team2": "Pittsburgh Pirates",
    "year": 2000
  },
  {
    "player": "Tommy Greene",
    "team1": "Atlanta Braves",
    "team2": "Philadelphia Phillies",
    "year": 1993
  },
  {
    "player": "Alejandro Pena",
    "team1": "Atlanta Braves",
    "team2": "Los Angeles Dodgers",
    "year": 1992
  },
  {
    "player": "Alejandro Pena",
    "team1": "Atlanta Braves",
    "team2": "New York Mets",
    "year": 1992
  },
  {
    "player": "Alejandro Pena",
    "team1": "Los Angeles Dodgers",
    "team2": "New York Mets",
    "year": 1991
  },
  {
    "player": "Orel Hershiser",
    "team1": "Cleveland Indians",
    "team2": "Los Angeles Dodgers",
    "year": 1997
  },
  {
    "player": "Dennis Martinez",
    "team1": "Cleveland Indians",
    "team2": "Montreal Expos",
    "year": 1996
  },
  {
    "player": "Deion Sanders",
    "team1": "Atlanta Braves",
    "team2": "New York Yankees",
    "year": 1992
  },
  {
    "player": "Joey Cora",
    "team1": "Chicago White Sox",
    "team2": "San Diego Padres",
    "year": 1992
  },
  {
    "player": "John Burkett",
    "team1": "San Francisco Giants",
    "team2": "Texas Rangers",
    "year": 1999
  },
  {
    "player": "Lee Smith",
    "team1": "Boston Red Sox",
    "team2": "St. Louis Cardinals",
    "year": 1991
  },
  {
    "player": "Rick Sutcliffe",
    "team1": "Baltimore Orioles",
    "team2": "Chicago Cubs",
    "year": 1993
  },
  {
    "player": "John Olerud",
    "team1": "New York Mets",
    "team2": "Toronto Blue Jays",
    "year": 1998
  },
  {
    "player": "Todd Frohwirth",
    "team1": "Baltimore Orioles",
    "team2": "Philadelphia Phillies",
    "year": 1992
  },
  {
    "player": "Mike Flanagan",
    "team1": "Baltimore Orioles",
    "team2": "Toronto Blue Jays",
    "year": 1992
  },
  {
    "player": "Glenallen Hill",
    "team1": "Cleveland Indians",
    "team2": "Toronto Blue Jays",
    "year": 1992
  },
  {
    "player": "Scott Bankhead",
    "team1": "Cincinnati Reds",
    "team2": "Seattle Mariners",
    "year": 1992
  },
  {
    "player": "Lenny Harris",
    "team1": "Cincinnati Reds",
    "team2": "Los Angeles Dodgers",
    "year": 1998
  },
  {
    "player": "Steve Bedrosian",
    "team1": "Minnesota Twins",
    "team2": "San Francisco Giants",
    "year": 1992
  },
  {
    "player": "Pete Harnisch",
    "team1": "Baltimore Orioles",
    "team2": "Houston Astros",
    "year": 1992
  },
  {
    "player": "Pete Harnisch",
    "team1": "Baltimore Orioles",
    "team2": "New York Mets",
    "year": 1996
  },
  {
    "player": "Pete Harnisch",
    "team1": "Houston Astros",
    "team2": "New York Mets",
    "year": 1996
  },
  {
    "player": "Mike Aldrete",
    "team1": "Cleveland Indians",
    "team2": "Montreal Expos",
    "year": 1992
  },
  {
    "player": "John Wetteland",
    "team1": "Los Angeles Dodgers",
    "team2": "Montreal Expos",
    "year": 1993
  },
  {
    "player": "John Wetteland",
    "team1": "Los Angeles Dodgers",
    "team2": "Texas Rangers",
    "year": 1999
  },
  {
    "player": "John Wetteland",
    "team1": "Montreal Expos",
    "team2": "Texas Rangers",
    "year": 1999
  },
  {
    "player": "Julio Machado",
    "team1": "Milwaukee Brewers",
    "team2": "New York Mets",
    "year": 1992
  },
  {
    "player": "Kevin Ritz",
    "team1": "Colorado Rockies",
    "team2": "Detroit Tigers",
    "year": 1996
  },
  {
    "player": "Kevin Tapani",
    "team1": "Chicago Cubs",
    "team2": "Minnesota Twins",
    "year": 1999
  },
  {
    "player": "Bob Tewksbury",
    "team1": "St. Louis Cardinals",
    "team2": "Texas Rangers",
    "year": 1996
  },
  {
    "player": "Oscar Azocar",
    "team1": "New York Yankees",
    "team2": "San Diego Padres",
    "year": 1992
  },
  {
    "player": "Steve Finley",
    "team1": "Baltimore Orioles",
    "team2": "San Diego Padres",
    "year": 1997
  },
  {
    "player": "Mike Hartley",
    "team1": "Los Angeles Dodgers",
    "team2": "Philadelphia Phillies",
    "year": 1993
  },
  {
    "player": "Erik Hanson",
    "team1": "Boston Red Sox",
    "team2": "Seattle Mariners",
    "year": 1996
  },
  {
    "player": "Andy Benes",
    "team1": "Arizona Diamondbacks",
    "team2": "San Diego Padres",
    "year": 1999
  },
  {
    "player": "Andy Benes",
    "team1": "Arizona Diamondbacks",
    "team2": "St. Louis Cardinals",
    "year": 1999
  },
  {
    "player": "Andy Benes",
    "team1": "San Diego Padres",
    "team2": "St. Louis Cardinals",
    "year": 1997
  },
  {
    "player": "Jose Vizcaino",
    "team1": "Chicago Cubs",
    "team2": "Los Angeles Dodgers",
    "year": 1993
  },
  {
    "player": "Travis Fryman",
    "team1": "Cleveland Indians",
    "team2": "Detroit Tigers",
    "year": 1999
  },
  {
    "player": "Mark Whiten",
    "team1": "Cleveland Indians",
    "team2": "St. Louis Cardinals",
    "year": 1995
  },
  {
    "player": "Mark Whiten",
    "team1": "Cleveland Indians",
    "team2": "Toronto Blue Jays",
    "year": 1992
  },
  {
    "player": "Mark Whiten",
    "team1": "St. Louis Cardinals",
    "team2": "Toronto Blue Jays",
    "year": 1995
  },
  {
    "player": "Jose Offerman",
    "team1": "Boston Red Sox",
    "team2": "Los Angeles Dodgers",
    "year": 2000
  },
  {
    "player": "Mike Fetters",
    "team1": "Anaheim Angels",
    "team2": "Milwaukee Brewers",
    "year": 1993
  },
  {
    "player": "Curt Schilling",
    "team1": "Baltimore Orioles",
    "team2": "Philadelphia Phillies",
    "year": 1999
  },
  {
    "player": "Jeff Conine",
    "team1": "Florida Marlins",
    "team2": "Kansas City Royals",
    "year": 1993
  },
  {
    "player": "Scott Erickson",
    "team1": "Baltimore Orioles",
    "team2": "Minnesota Twins",
    "year": 1996
  },
  {
    "player": "Kevin Brown",
    "team1": "Milwaukee Brewers",
    "team2": "San Diego Padres",
    "year": 1999
  },
  {
    "player": "Kevin Brown",
    "team1": "Milwaukee Brewers",
    "team2": "Texas Rangers",
    "year": 1992
  },
  {
    "player": "Kevin Brown",
    "team1": "San Diego Padres",
    "team2": "Texas Rangers",
    "year": 1999
  },
  {
    "player": "Carlos Martinez",
    "team1": "Chicago White Sox",
    "team2": "Cleveland Indians",
    "year": 1992
  },
  {
    "player": "Jeromy Burnitz",
    "team1": "Milwaukee Brewers",
    "team2": "New York Mets",
    "year": 1999
  },
  {
    "player": "Tony Fossas",
    "team1": "Boston Red Sox",
    "team2": "Milwaukee Brewers",
    "year": 1992
  },
  {
    "player": "Tim Costo",
    "team1": "Cincinnati Reds",
    "team2": "Cleveland Indians",
    "year": 1993
  },
  {
    "player": "Jose Mesa",
    "team1": "Baltimore Orioles",
    "team2": "Cleveland Indians",
    "year": 1997
  },
  {
    "player": "Jerald Clark",
    "team1": "Colorado Rockies",
    "team2": "San Diego Padres",
    "year": 1993
  },
  {
    "player": "Turner Ward",
    "team1": "Cleveland Indians",
    "team2": "Pittsburgh Pirates",
    "year": 1999
  },
  {
    "player": "Shawn Boskie",
    "team1": "Anaheim Angels",
    "team2": "Chicago Cubs",
    "year": 1997
  },
  {
    "player": "Dave Gallagher",
    "team1": "Anaheim Angels",
    "team2": "Baltimore Orioles",
    "year": 1992
  },
  {
    "player": "Wilson Alvarez",
    "team1": "Chicago White Sox",
    "team2": "Tampa Bay Rays",
    "year": 1999
  },
  {
    "player": "Paul Sorrento",
    "team1": "Cleveland Indians",
    "team2": "Minnesota Twins",
    "year": 1995
  },
  {
    "player": "Greg Vaughn",
    "team1": "Milwaukee Brewers",
    "team2": "San Diego Padres",
    "year": 1999
  },
  {
    "player": "Todd Zeile",
    "team1": "Baltimore Orioles",
    "team2": "St. Louis Cardinals",
    "year": 1997
  },
  {
    "player": "Dean Palmer",
    "team1": "Kansas City Royals",
    "team2": "Texas Rangers",
    "year": 1999
  },
  {
    "player": "Tino Martinez",
    "team1": "New York Yankees",
    "team2": "Seattle Mariners",
    "year": 1999
  },
  {
    "player": "David Justice",
    "team1": "Atlanta Braves",
    "team2": "Cleveland Indians",
    "year": 1999
  },
  {
    "player": "Kenny Rogers",
    "team1": "Oakland Athletics",
    "team2": "Texas Rangers",
    "year": 1999
  },
  {
    "player": "Rod Beck",
    "team1": "Chicago Cubs",
    "team2": "San Francisco Giants",
    "year": 1999
  },
  {
    "player": "Eric Plunk",
    "team1": "Cleveland Indians",
    "team2": "New York Yankees",
    "year": 1996
  },
  {
    "player": "David Wells",
    "team1": "New York Yankees",
    "team2": "Toronto Blue Jays",
    "year": 1999
  },
  {
    "player": "Chris Haney",
    "team1": "Kansas City Royals",
    "team2": "Montreal Expos",
    "year": 1993
  },
  {
    "player": "Royce Clayton",
    "team1": "San Francisco Giants",
    "team2": "St. Louis Cardinals",
    "year": 1997
  },
  {
    "player": "Kenny Lofton",
    "team1": "Atlanta Braves",
    "team2": "Cleveland Indians",
    "year": 1999
  },
  {
    "player": "Chad Curtis",
    "team1": "Anaheim Angels",
    "team2": "New York Yankees",
    "year": 1999
  },
  {
    "player": "Dave Burba",
    "team1": "San Francisco Giants",
    "team2": "Seattle Mariners",
    "year": 1992
  },
  {
    "player": "Denny Neagle",
    "team1": "Atlanta Braves",
    "team2": "Pittsburgh Pirates",
    "year": 1999
  },
  {
    "player": "Jeff Fassero",
    "team1": "Montreal Expos",
    "team2": "Seattle Mariners",
    "year": 1998
  },
  {
    "player": "Chuck Knoblauch",
    "team1": "Minnesota Twins",
    "team2": "New York Yankees",
    "year": 1998
  },
  {
    "player": "J.T. Snow",
    "team1": "New York Yankees",
    "team2": "San Francisco Giants",
    "year": 1999
  },
  {
    "player": "Cliff Floyd",
    "team1": "Florida Marlins",
    "team2": "Montreal Expos",
    "year": 1999
  },
  {
    "player": "Jose Valentin",
    "team1": "Chicago Cubs",
    "team2": "Milwaukee Brewers",
    "year": 1996
  },
  {
    "player": "Manny Ramirez",
    "team1": "Boston Red Sox",
    "team2": "Cleveland Indians",
    "year": 1999
  },
  {
    "player": "Damion Easley",
    "team1": "Anaheim Angels",
    "team2": "Detroit Tigers",
    "year": 1999
  },
  {
    "player": "Randy Johnson",
    "team1": "Arizona Diamondbacks",
    "team2": "Seattle Mariners",
    "year": 1999
  },
  {
    "player": "Moises Alou",
    "team1": "Houston Astros",
    "team2": "Montreal Expos",
    "year": 2000
  },
  {
    "player": "Raul Mondesi",
    "team1": "Los Angeles Dodgers",
    "team2": "Toronto Blue Jays",
    "year": 2000
  },
  {
    "player": "Brant Brown",
    "team1": "Chicago Cubs",
    "team2": "Pittsburgh Pirates",
    "year": 1999
  },
  {
    "player": "Jeff Kent",
    "team1": "Cleveland Indians",
    "team2": "San Francisco Giants",
    "year": 1999
  },
  {
    "player": "Brian Giles",
    "team1": "Cleveland Indians",
    "team2": "Pittsburgh Pirates",
    "year": 1999
  },
  {
    "player": "Bernard Gilkey",
    "team1": "Arizona Diamondbacks",
    "team2": "New York Mets",
    "year": 1999
  },
  {
    "player": "Mike Piazza",
    "team1": "Los Angeles Dodgers",
    "team2": "New York Mets",
    "year": 1999
  }
]